[
  {
    "D": -15,
    "d_K": 15,
    "j": 1,
    "a2_str": "7",
    "a2_type": "t_INT",
    "verdict": "OTHER",
    "value_str": "None",
    "Re_str": "2.904737509655562664",
    "Im_str": "0",
    "Q_residual_str": "2.503704693127326055 E-19",
    "sqrt_residual_str": "0.E-18",
    "Rf_str": "2.904737509655562664"
  },
  {
    "D": -15,
    "d_K": 15,
    "j": 2,
    "a2_str": "-7",
    "a2_type": "t_INT",
    "verdict": "OTHER",
    "value_str": "None",
    "Re_str": "3.630921887069453330",
    "Im_str": "0",
    "Q_residual_str": "1.0450836861178759504 E-18",
    "sqrt_residual_str": "2.168404344971008868 E-19",
    "Rf_str": "3.630921887069453330"
  },
  {
    "D": -15,
    "d_K": 15,
    "j": 3,
    "a2_str": "Mod(-1/9*y^3 + 1/9*y, y^4 + 8*y^2 + 81)",
    "a2_type": "t_POLMOD",
    "verdict": "OTHER",
    "value_str": "None",
    "Re_str": "4.741080748781642839",
    "Im_str": "-2.201844847853939973",
    "Q_residual_str": "2.0499484302350238069 E-17",
    "sqrt_residual_str": "None",
    "Rf_str": "4.741080748781642839 - 2.201844847853939973*I"
  },
  {
    "D": -20,
    "d_K": 5,
    "j": 1,
    "a2_str": "4",
    "a2_type": "t_INT",
    "verdict": "OTHER",
    "value_str": "None",
    "Re_str": "3.726779962499649494",
    "Im_str": "0",
    "Q_residual_str": "1.0257731664185484164 E-18",
    "sqrt_residual_str": "0.E-18",
    "Rf_str": "3.726779962499649494"
  },
  {
    "D": -20,
    "d_K": 5,
    "j": 2,
    "a2_str": "-4",
    "a2_type": "t_INT",
    "verdict": "OTHER",
    "value_str": "None",
    "Re_str": "4.472135954999579393",
    "Im_str": "0",
    "Q_residual_str": "1.2309277997022580996 E-18",
    "sqrt_residual_str": "4.336808689942017736 E-19",
    "Rf_str": "4.472135954999579393"
  },
  {
    "D": -20,
    "d_K": 5,
    "j": 3,
    "a2_str": "Mod(y, y^8 + 24*y^6 + 496*y^4 + 6144*y^2 + 65536)",
    "a2_type": "t_POLMOD",
    "verdict": "OTHER",
    "value_str": "None",
    "Re_str": "9.604864580585900548",
    "Im_str": "0.4525591460919911410",
    "Q_residual_str": "9.460505077564154242 E-19",
    "sqrt_residual_str": "None",
    "Rf_str": "9.604864580585900548 + 0.4525591460919911410*I"
  },
  {
    "D": -24,
    "d_K": 6,
    "j": 1,
    "a2_str": "4",
    "a2_type": "t_INT",
    "verdict": "OTHER",
    "value_str": "None",
    "Re_str": "4.199125273342591026",
    "Im_str": "0",
    "Q_residual_str": "0.E-18",
    "sqrt_residual_str": "4.336808689942017736 E-19",
    "Rf_str": "4.199125273342591026"
  },
  {
    "D": -24,
    "d_K": 6,
    "j": 2,
    "a2_str": "-4",
    "a2_type": "t_INT",
    "verdict": "OTHER",
    "value_str": "None",
    "Re_str": "5.878775382679627436",
    "Im_str": "0",
    "Q_residual_str": "1.4059972264791295643 E-17",
    "sqrt_residual_str": "4.336808689942017736 E-19",
    "Rf_str": "5.878775382679627436"
  },
  {
    "D": -24,
    "d_K": 6,
    "j": 3,
    "a2_str": "Mod(y, y^12 + 10*y^10 + 216*y^8 + 6848*y^6 + 55296*y^4 + 655360*y^2 + 16777216)",
    "a2_type": "t_POLMOD",
    "verdict": "OTHER",
    "value_str": "None",
    "Re_str": "7.861223678912377105",
    "Im_str": "-4.061692520937533397",
    "Q_residual_str": "1.4285345439794997867 E-18",
    "sqrt_residual_str": "None",
    "Rf_str": "7.861223678912377105 - 4.061692520937533397*I"
  },
  {
    "D": -35,
    "d_K": 35,
    "j": 1,
    "a2_str": "0",
    "a2_type": "t_INT",
    "verdict": "OTHER",
    "value_str": "None",
    "Re_str": "5.916079783099616042",
    "Im_str": "0",
    "Q_residual_str": "1.1374531853307891944 E-18",
    "sqrt_residual_str": "4.336808689942017736 E-19",
    "Rf_str": "5.916079783099616042"
  },
  {
    "D": -35,
    "d_K": 35,
    "j": 2,
    "a2_str": "0",
    "a2_type": "t_INT",
    "verdict": "OTHER",
    "value_str": "None",
    "Re_str": "7.668992311425428204",
    "Im_str": "0",
    "Q_residual_str": "5.687265926653945972 E-19",
    "sqrt_residual_str": "4.336808689942017736 E-19",
    "Rf_str": "7.668992311425428204"
  },
  {
    "D": -35,
    "d_K": 35,
    "j": 3,
    "a2_str": "Mod(y, y^2 + 6)",
    "a2_type": "t_POLMOD",
    "verdict": "OTHER",
    "value_str": "None",
    "Re_str": "6.274453922387190365",
    "Im_str": "-0.6355747387737137138",
    "Q_residual_str": "5.908362815474969354 E-17",
    "sqrt_residual_str": "None",
    "Rf_str": "6.274453922387190365 - 0.6355747387737137138*I"
  },
  {
    "D": -35,
    "d_K": 35,
    "j": 4,
    "a2_str": "Mod(y, y^2 + 6)",
    "a2_type": "t_POLMOD",
    "verdict": "OTHER",
    "value_str": "None",
    "Re_str": "7.526203459611698313",
    "Im_str": "-3.378138102577284950",
    "Q_residual_str": "8.836242340094780704 E-19",
    "sqrt_residual_str": "None",
    "Rf_str": "7.526203459611698313 - 3.378138102577284950*I"
  },
  {
    "D": -35,
    "d_K": 35,
    "j": 5,
    "a2_str": "Mod(325/1972866504*y^7 - 5639/140919036*y^5 + 839125/93946024*y^3 - 53007085/164405542*y, y^8 - 210*y^6 + 43113*y^4 - 3674880*y^2 + 257409936)",
    "a2_type": "t_POLMOD",
    "verdict": "OTHER",
    "value_str": "None",
    "Re_str": "14.120499816806511838",
    "Im_str": "-3.883815829894490991",
    "Q_residual_str": "0.E-17",
    "sqrt_residual_str": "None",
    "Rf_str": "14.120499816806511838 - 3.883815829894490991*I"
  },
  {
    "D": -40,
    "d_K": 10,
    "j": 1,
    "a2_str": "4",
    "a2_type": "t_INT",
    "verdict": "OTHER",
    "value_str": "None",
    "Re_str": "6.542643434831129652",
    "Im_str": "0",
    "Q_residual_str": "4.212647077981317565 E-19",
    "sqrt_residual_str": "4.336808689942017736 E-19",
    "Rf_str": "6.542643434831129652"
  },
  {
    "D": -40,
    "d_K": 10,
    "j": 2,
    "a2_str": "-4",
    "a2_type": "t_INT",
    "verdict": "OTHER",
    "value_str": "None",
    "Re_str": "9.486832980505137996",
    "Im_str": "0",
    "Q_residual_str": "2.2099756757541691182 E-18",
    "sqrt_residual_str": "0.E-18",
    "Rf_str": "9.486832980505137996"
  },
  {
    "D": -40,
    "d_K": 10,
    "j": 3,
    "a2_str": "Mod(y, y^20 + 10*y^18 - 20*y^16 + 2640*y^14 + 22400*y^12 - 652288*y^10 + 5734400*y^8 + 173015040*y^6 - 335544320*y^4 + 42949672960*y^2 + 1099511627776)",
    "a2_type": "t_POLMOD",
    "verdict": "OTHER",
    "value_str": "None",
    "Re_str": "8.600291964546143915",
    "Im_str": "-5.448426554733049677",
    "Q_residual_str": "1.3746700725751045498 E-18",
    "sqrt_residual_str": "None",
    "Rf_str": "8.600291964546143915 - 5.448426554733049677*I"
  },
  {
    "D": -88,
    "d_K": 22,
    "j": 1,
    "a2_str": "4",
    "a2_type": "t_INT",
    "verdict": "OTHER",
    "value_str": "None",
    "Re_str": "13.327756718715498460",
    "Im_str": "0",
    "Q_residual_str": "0.E-17",
    "sqrt_residual_str": "0.E-18",
    "Rf_str": "13.327756718715498460"
  },
  {
    "D": -88,
    "d_K": 22,
    "j": 2,
    "a2_str": "-4",
    "a2_type": "t_INT",
    "verdict": "OTHER",
    "value_str": "None",
    "Re_str": "20.736574938166741188",
    "Im_str": "0",
    "Q_residual_str": "1.2184150029779385893 E-18",
    "sqrt_residual_str": "0.E-17",
    "Rf_str": "20.736574938166741188"
  },
  {
    "D": -88,
    "d_K": 22,
    "j": 3,
    "a2_str": "Mod(y, y^44 + 14*y^42 + 10*y^40 + 148*y^38 + 70624*y^36 + 1530400*y^34 - 4300928*y^32 - 74770432*y^30 + 5447593984*y^28 + 132946034688*y^26 + 838994493440*y^24 - 7547503247360*y^22 + 214782590320640*y^20 + 8712751329312768*y^18 + 91395460949868544*y^16 - 321136560147791872*y^14 - 4728920346227376128*y^12 + 430769304357987942400*y^10 + 5088995521334622552064*y^8 + 2730118122909013639168*y^6 + 47223664828696452136960*y^4 + 16924961474604808445886464*y^2 + 309485009821345068724781056)",
    "a2_type": "t_POLMOD",
    "verdict": "OTHER",
    "value_str": "None",
    "Re_str": "26.738192588726641630",
    "Im_str": "0.22982249174804112316",
    "Q_residual_str": "0.E-17",
    "sqrt_residual_str": "None",
    "Rf_str": "26.738192588726641630 + 0.22982249174804112316*I"
  }
]